README.rst
_description.org
lh-agpl3-LICENSE.txt
pyproject.toml
setup.py
bin/aasMarmeeManage.cs
bin/aasMarmeeQmailHere.cs
bin/dsnMsgPlugin.py
bin/marmee-admin.cs
bin/marmee-assemble.cs
bin/marmee-binsPrep.cs
bin/marmeeDaemonSysd.cs
bin/marmeeDsnPlugin.cs
bin/marmeeDsnProc.cs
bin/marmeeGmailOauth2.cs
bin/marmeeNotmuch.cs
bin/marmeeOfflineimap.cs
bin/marmeeQmailObsoleted.cs
bin/marmeeRuns.cs
bin/marmeeSend.cs
bin/marmeeSendExample.py
bin/marmeeTracking.cs
bin/pkgMarmeeManage.cs
bin/sendOauthWebStart.py
bisos/__init__.py
bisos.marmee.egg-info/PKG-INFO
bisos.marmee.egg-info/SOURCES.txt
bisos.marmee.egg-info/dependency_links.txt
bisos.marmee.egg-info/not-zip-safe
bisos.marmee.egg-info/requires.txt
bisos.marmee.egg-info/top_level.txt
bisos/marmee/__init__.py
bisos/marmee/aasInMailFps.py
bisos/marmee/aasMailFps.py
bisos/marmee/aasOutMailFps.py
bisos/marmee/gmailOauth2.py
bisos/marmee/maildirObsolete.py
bisos/marmee/maildrop.py
bisos/marmee/marmeeCurrentsLib.py
bisos/marmee/marmeeDaemonSysd.py
bisos/marmee/marmeeGmail.py
bisos/marmee/marmeeMaildir.py
bisos/marmee/marmeeMsgLib.py
bisos/marmee/marmeeOfflineimap.py
bisos/marmee/marmeePkgThis.py
bisos/marmee/marmeeQmailHere.py
bisos/marmee/marmeeSend.py
bisos/marmee/marmeeSendLib.py
bisos/marmee/marmeeTrackingLib.py
bisos/marmee/qmailOrAcct.py
bisos/marmee/qmailOrAcctAlias.py
bisos/marmee/x822In.py
bisos/marmee/x822Lib.py
bisos/marmee/x822Out.py