Metadata-Version: 2.2
Name: bisos.marmee
Version: 0.87
Summary: bisos.marmee:  Python Command-Services for MARMEE (Multi-Account Resident Mail Exchanger Envinronment) is a collection of CSs for maintaining multiple mail sending and host resident mailboxes.
Author: Mohsen Banan
Author-email: libre@mohsen.1.banan.byname.net
Maintainer: Mohsen Banan
Maintainer-email: libre@mohsen.1.banan.byname.net
License: AGPL
Classifier: Development Status :: 5 - Production/Stable
Classifier: Intended Audience :: Developers
Classifier: License :: OSI Approved :: GNU Affero General Public License v3
Classifier: Operating System :: POSIX
Classifier: Programming Language :: Python
Classifier: Topic :: Software Development :: Libraries
Classifier: Topic :: Software Development :: Libraries :: Python Modules
Requires-Dist: bisos
Requires-Dist: bisos.b
Requires-Dist: bisos.banna
Requires-Dist: bisos.basics
Requires-Dist: bisos.binsprep
Requires-Dist: bisos.bpo
Requires-Dist: bisos.common
Requires-Dist: bisos.csPlayer
Requires-Dist: bisos.currents
Requires-Dist: bisos.debian
Requires-Dist: bisos.facter
Requires-Dist: bisos.qmail
Requires-Dist: setuptools==75.8.0
Dynamic: author
Dynamic: author-email
Dynamic: classifier
Dynamic: description
Dynamic: license
Dynamic: maintainer
Dynamic: maintainer-email
Dynamic: requires-dist
Dynamic: summary
